perspective/__init__.py
perspective/attributes.py
perspective/errors.py
perspective/main.py
perspective/utils.py
perspective.py-0.3.4.dist-info/LICENSE
perspective.py-0.3.4.dist-info/METADATA
perspective.py-0.3.4.dist-info/WHEEL
perspective.py-0.3.4.dist-info/top_level.txt
perspective.py-0.3.4.dist-info/RECORD
